process_pilot/__init__.py
process_pilot/graph.py
process_pilot/pilot.py
process_pilot/plugin.py
process_pilot/process.py
process_pilot/py.typed
process_pilot/shutdown_detector.py
process_pilot/types.py
process_pilot/plugins/__init__.py
process_pilot/plugins/file_ready.py
process_pilot/plugins/pipe_ready.py
process_pilot/plugins/tcp_control.py
process_pilot/plugins/tcp_ready.py
process_pilot-0.4.6.dist-info/METADATA
process_pilot-0.4.6.dist-info/WHEEL
process_pilot-0.4.6.dist-info/entry_points.txt
process_pilot-0.4.6.dist-info/licenses/LICENSE
process_pilot-0.4.6.dist-info/RECORD
