Metadata-Version: 2.4
Name: process-pilot
Version: 0.4.6
Summary: Process manager for Python
Project-URL: Repository, https://github.com/engineerjames/process-pilot
Project-URL: Documentation, https://process-pilot.readthedocs.io/
Author-email: James Armes <jamesleearmes@gmail.com>
License-File: LICENSE
Keywords: management,monitoring,process
Requires-Python: <3.14,>=3.10
Requires-Dist: graphviz>=0.10
Requires-Dist: psutil>=5.4.0
Requires-Dist: pydantic>=2.0.0
Requires-Dist: pywin32>=300; sys_platform == 'win32'
Requires-Dist: pyyaml!=5.4.0,!=5.4.1,!=6.0.0
